raise_.py
raise-1.1.9.dist-info/LICENSE
raise-1.1.9.dist-info/METADATA
raise-1.1.9.dist-info/WHEEL
raise-1.1.9.dist-info/top_level.txt
raise-1.1.9.dist-info/RECORD
