Metadata-Version: 2.1
Name: raise
Version: 1.1.9
Summary: Raise exceptions with a function instead of a statement.
Home-page: https://github.com/mentalisttraceur/python-raise
Author: Alexander Kozhevnikov
Author-email: mentalisttraceur@gmail.com
License: 0BSD
Platform: UNKNOWN
Classifier: Development Status :: 6 - Mature
Classifier: Programming Language :: Python :: 3
Classifier: Programming Language :: Python :: 2
Classifier: Operating System :: OS Independent
